docs/config.yaml
paperpile_notion/commands.py
paperpile_notion/from_bib.py
paperpile_notion/models/__init__.py
paperpile_notion/models/_models.py
paperpile_notion/models/cells.py
paperpile_notion/models/validators.py
paperpile_notion/utils/__init__.py
paperpile_notion/utils/bibtex.py
paperpile_notion/utils/notion.py
paperpile_notion/utils/printers.py
paperpile_notion-0.3.5.dist-info/entry_points.txt
paperpile_notion-0.3.5.dist-info/LICENSE
paperpile_notion-0.3.5.dist-info/WHEEL
paperpile_notion-0.3.5.dist-info/METADATA
paperpile_notion-0.3.5.dist-info/RECORD
