Metadata-Version: 2.1
Name: paperpile-notion
Version: 0.3.5
Summary: Sync Notion with Paperpile
Home-page: https://github.com/jmuchovej/paperpile-notion
License: MIT
Author: J Muchovej
Author-email: 5000729+jmuchovej@users.noreply.github.com
Requires-Python: >=3.7.1,<4.0
Classifier: License :: OSI Approved :: MIT License
Classifier: Programming Language :: Python :: 3
Classifier: Programming Language :: Python :: 3.8
Classifier: Programming Language :: Python :: 3.9
Requires-Dist: attrs (>=21.2.0,<22.0.0)
Requires-Dist: bibtexparser (>=1.2.0,<2.0.0)
Requires-Dist: click (>=8.0.1,<9.0.0)
Requires-Dist: emojis (>=0.6.0,<0.7.0)
Requires-Dist: fuzzywuzzy (>=0.18.0,<0.19.0)
Requires-Dist: notion-client (>=0.6.0,<0.7.0)
Requires-Dist: python-Levenshtein (>=0.12.2,<0.13.0)
Requires-Dist: ruamel.yaml (>=0.17.13,<0.18.0)
Project-URL: Repository, https://github.com/jmuchovej/paperpile-notion
